{
  "de": {
    "login": {
      "title": "Anmelden oder Konto erstellen",
      "subtitle": "Bitte geben Sie Ihre E-Mail-Adresse ein",
      "steps": {
        "email": {
          "label": "E-Mail-Adresse",
          "placeholder": "beispiel@firma.com",
          "button": "Weiter"
        },
        "code": {
          "note": "Bitte prüfen Sie Ihr E-Mail-Postfach und geben Sie den Code ein, um fortzufahren.",
          "label": "Login-Code eingeben",
          "placeholder": "123456",
          "button": "Weiter",
          "links": {
            "back": "Zurück",
            "resend": "Neuen Code senden"
          }
        }
      }
    }
  },
  "en": {
    "login": {
      "title": "Sign in or create an account",
      "subtitle": "Please enter your email address",
      "steps": {
        "email": {
          "label": "Email address",
          "placeholder": "example@company.com",
          "button": "Next"
        },
        "code": {
          "note": "Please check your inbox and enter the code to continue.",
          "label": "Enter login code",
          "placeholder": "123456",
          "button": "Next",
          "links": {
            "back": "Back",
            "resend": "Send new code"
          }
        }
      }
    }
  }
}